sate/__init__.py
sate/__main__.py
sate/app.py
sate/parse.py
sate/rules.py
sate/types.py
sate-1.12.0.data/scripts/sate
sate-1.12.0.dist-info/DESCRIPTION.rst
sate-1.12.0.dist-info/METADATA
sate-1.12.0.dist-info/RECORD
sate-1.12.0.dist-info/WHEEL
sate-1.12.0.dist-info/metadata.json
sate-1.12.0.dist-info/top_level.txt
