Metadata-Version: 2.0
Name: sate
Version: 1.12.0
Summary: Simple command-line task runner
Home-page: https://github.com/nicholasbishop/sate
Author: Nicholas Bishop
Author-email: nicholasbishop@gmail.com
License: UNKNOWN
Platform: UNKNOWN
Requires-Dist: attrs (~=17.3.0)
Requires-Dist: parsy (~=1.2.0)
Requires-Dist: toposort (~=1.5)
